MQTTNetLyzer/__init__.py
MQTTNetLyzer/analyzer.py
MQTTNetLyzer/calculate_features.py
MQTTNetLyzer/csv_writer.py
MQTTNetLyzer/extract_features.py
MQTTNetLyzer/helper_functions.py
MQTTNetLyzer/main.py
MQTTNetLyzer/running_stats.py
MQTTNetLyzer/session.py
MQTTNetLyzer/variables.py
mqttnetlyzer-1.0.0.dist-info/licenses/LICENSE
mqttnetlyzer-1.0.0.dist-info/METADATA
mqttnetlyzer-1.0.0.dist-info/WHEEL
mqttnetlyzer-1.0.0.dist-info/entry_points.txt
mqttnetlyzer-1.0.0.dist-info/top_level.txt
mqttnetlyzer-1.0.0.dist-info/RECORD
