Metadata-Version: 2.4
Name: MQTTNetLyzer
Version: 1.0.0
Summary: The MQTT Layer Session Analyzer
Home-page: https://github.com/adityaraj218/MQTTNetLyzer
Author: Aditya Raj
Author-email: adityaraj867604@gmail.com
License: GPLv3
Classifier: Programming Language :: Python :: 3
Classifier: License :: OSI Approved :: GNU General Public License v3 (GPLv3)
Classifier: Operating System :: OS Independent
License-File: LICENSE
Requires-Dist: scapy==2.5.0
Dynamic: author
Dynamic: author-email
Dynamic: classifier
Dynamic: description
Dynamic: description-content-type
Dynamic: home-page
Dynamic: license
Dynamic: license-file
Dynamic: requires-dist
Dynamic: summary
